{"408960061": {"chat_id": null, "content_hash": null, "message_id": null, "sent_at": null}, "408961061": {"chat_id": null, "content_hash": null, "message_id": null, "sent_at": null}, "408962061": {"chat_id": null, "content_hash": null, "message_id": null, "sent_at": null}, "408963061": {"chat_id": null, "content_hash": null, "message_id": null, "sent_at": null}, "408971061": {"chat_id": null, "content_hash": null, "message_id": null, "sent_at": null}, "408978061": {"chat_id": null, "content_hash": null, "message_id": null, "sent_at": null}, "408980061": {"chat_id": null, "content_hash": null, "message_id": null, "sent_at": null}, "408983061": {"chat_id": null, "content_hash": null, "message_id": null, "sent_at": null}, "408985061": {"chat_id": null, "content_hash": null, "message_id": null, "sent_at": null}, "408991061": {"chat_id": null, "content_hash": null, "message_id": null, "sent_at": null}, "408993061": {"chat_id": null, "content_hash": null, "message_id": null, "sent_at": null}, "408995061": {"chat_id": null, "content_hash": null, "message_id": null, "sent_at": null}, "409004061": {"chat_id": null, "content_hash": null, "message_id": null, "sent_at": null}, "409014061": {"chat_id": null, "content_hash": null, "message_id": null, "sent_at": null}, "409016061": {"chat_id": null, "content_hash": null, "message_id": null, "sent_at": null}, "409017061": {"chat_id": null, "content_hash": null, "message_id": null, "sent_at": null}, "409018061": {"chat_id": null, "content_hash": null, "message_id": null, "sent_at": null}, "409020061": {"chat_id": null, "content_hash": null, "message_id": null, "sent_at": null}, "409021061": {"chat_id": null, "content_hash": null, "message_id": null, "sent_at": null}, "409023061": {"chat_id": null, "content_hash": null, "message_id": null, "sent_at": null}, "409028061": {"chat_id": null, "content_hash": null, "message_id": null, "sent_at": null}, "409029061": {"chat_id": null, "content_hash": null, "message_id": null, "sent_at": null}, "409034061": {"chat_id": null, "content_hash": null, "message_id": null, "sent_at": null}, "409035061": {"chat_id": null, "content_hash": null, "message_id": null, "sent_at": null}, "409041061": {"chat_id": null, "content_hash": null, "message_id": null, "sent_at": null}, "409042061": {"chat_id": null, "content_hash": null, "message_id": null, "sent_at": null}, "409052061": {"chat_id": null, "content_hash": null, "message_id": null, "sent_at": null}, "409053061": {"chat_id": null, "content_hash": null, "message_id": null, "sent_at": null}, "409054061": {"chat_id": null, "content_hash": null, "message_id": null, "sent_at": null}, "409057061": {"chat_id": null, "content_hash": null, "message_id": null, "sent_at": null}, "409058061": {"chat_id": null, "content_hash": null, "message_id": null, "sent_at": null}, "409059061": {"chat_id": null, "content_hash": null, "message_id": null, "sent_at": null}, "409061061": {"chat_id": null, "content_hash": null, "message_id": null, "sent_at": null}, "409062061": {"chat_id": null, "content_hash": null, "message_id": null, "sent_at": null}, "409063061": {"chat_id": null, "content_hash": null, "message_id": null, "sent_at": null}, "409064061": {"chat_id": null, "content_hash": null, "message_id": null, "sent_at": null}, "409073061": {"chat_id": null, "content_hash": null, "message_id": null, "sent_at": null}, "409074061": {"chat_id": null, "content_hash": null, "message_id": null, "sent_at": null}, "409075061": {"chat_id": null, "content_hash": null, "message_id": null, "sent_at": null}, "409092061": {"chat_id": null, "content_hash": null, "message_id": null, "sent_at": null}, "409100061": {"chat_id": null, "content_hash": null, "message_id": null, "sent_at": null}, "409106061": {"chat_id": null, "content_hash": null, "message_id": null, "sent_at": null}, "409115061": {"chat_id": null, "content_hash": null, "message_id": null, "sent_at": null}, "409116061": {"chat_id": null, "content_hash": null, "message_id": null, "sent_at": null}, "409118061": {"chat_id": null, "content_hash": null, "message_id": null, "sent_at": null}, "409119061": {"chat_id": null, "content_hash": null, "message_id": null, "sent_at": null}, "409120061": {"chat_id": null, "content_hash": null, "message_id": null, "sent_at": null}, "409121061": {"chat_id": null, "content_hash": null, "message_id": null, "sent_at": null}, "409124061": {"chat_id": null, "content_hash": null, "message_id": null, "sent_at": null}, "409125061": {"chat_id": null, "content_hash": null, "message_id": null, "sent_at": null}, "409126061": {"chat_id": null, "content_hash": null, "message_id": null, "sent_at": null}, "409127061": {"chat_id": null, "content_hash": null, "message_id": null, "sent_at": null}, "409130061": {"chat_id": null, "content_hash": null, "message_id": null, "sent_at": null}, "409131061": {"chat_id": null, "content_hash": null, "message_id": null, "sent_at": null}, "409138061": {"chat_id": null, "content_hash": null, "message_id": null, "sent_at": null}, "409139061": {"chat_id": null, "content_hash": null, "message_id": null, "sent_at": null}, "409140061": {"chat_id": null, "content_hash": null, "message_id": null, "sent_at": null}, "409141061": {"chat_id": null, "content_hash": null, "message_id": null, "sent_at": null}, "409142061": {"chat_id": null, "content_hash": null, "message_id": null, "sent_at": null}, "409143061": {"chat_id": null, "content_hash": null, "message_id": null, "sent_at": null}, "409144061": {"chat_id": null, "content_hash": null, "message_id": null, "sent_at": null}, "409145061": {"chat_id": null, "content_hash": null, "message_id": null, "sent_at": null}, "409147061": {"chat_id": null, "content_hash": null, "message_id": null, "sent_at": null}, "409148061": {"chat_id": null, "content_hash": null, "message_id": null, "sent_at": null}, "409149061": {"chat_id": null, "content_hash": null, "message_id": null, "sent_at": null}, "409150061": {"chat_id": null, "content_hash": null, "message_id": null, "sent_at": null}, "409152061": {"chat_id": null, "content_hash": null, "message_id": null, "sent_at": null}, "409154061": {"chat_id": null, "content_hash": null, "message_id": null, "sent_at": null}, "409156061": {"chat_id": null, "content_hash": null, "message_id": null, "sent_at": null}, "409157061": {"chat_id": null, "content_hash": null, "message_id": null, "sent_at": null}, "409158061": {"chat_id": null, "content_hash": null, "message_id": null, "sent_at": null}, "409160061": {"chat_id": null, "content_hash": null, "message_id": null, "sent_at": null}, "409161061": {"chat_id": null, "content_hash": null, "message_id": null, "sent_at": null}, "409162061": {"chat_id": null, "content_hash": null, "message_id": null, "sent_at": null}, "409163061": {"chat_id": null, "content_hash": null, "message_id": null, "sent_at": null}, "409167061": {"chat_id": null, "content_hash": null, "message_id": null, "sent_at": null}, "409168061": {"chat_id": null, "content_hash": null, "message_id": null, "sent_at": null}, "409169061": {"chat_id": null, "content_hash": null, "message_id": null, "sent_at": null}, "409170061": {"chat_id": null, "content_hash": null, "message_id": null, "sent_at": null}, "409171061": {"chat_id": null, "content_hash": null, "message_id": null, "sent_at": null}, "409172061": {"chat_id": null, "content_hash": null, "message_id": null, "sent_at": null}, "409173061": {"chat_id": null, "content_hash": null, "message_id": null, "sent_at": null}, "409175061": {"chat_id": null, "content_hash": null, "message_id": null, "sent_at": null}, "409176061": {"chat_id": null, "content_hash": null, "message_id": null, "sent_at": null}, "409177061": {"chat_id": null, "content_hash": null, "message_id": null, "sent_at": null}, "409178061": {"chat_id": null, "content_hash": null, "message_id": null, "sent_at": null}, "409179061": {"chat_id": null, "content_hash": null, "message_id": null, "sent_at": null}, "409180061": {"chat_id": null, "content_hash": null, "message_id": null, "sent_at": null}, "409181061": {"chat_id": null, "content_hash": null, "message_id": null, "sent_at": null}, "409185061": {"chat_id": null, "content_hash": null, "message_id": null, "sent_at": null}, "409186061": {"chat_id": null, "content_hash": null, "message_id": null, "sent_at": null}, "409187061": {"chat_id": null, "content_hash": null, "message_id": null, "sent_at": null}, "409189061": {"chat_id": null, "content_hash": null, "message_id": null, "sent_at": null}, "409191061": {"chat_id": null, "content_hash": null, "message_id": null, "sent_at": null}, "409193061": {"chat_id": null, "content_hash": null, "message_id": null, "sent_at": null}, "409194061": {"chat_id": null, "content_hash": null, "message_id": null, "sent_at": null}, "409195061": {"chat_id": null, "content_hash": null, "message_id": null, "sent_at": null}, "409196061": {"chat_id": null, "content_hash": null, "message_id": null, "sent_at": null}, "409197061": {"chat_id": null, "content_hash": null, "message_id": null, "sent_at": null}, "409198061": {"chat_id": null, "content_hash": null, "message_id": null, "sent_at": null}, "409199061": {"chat_id": null, "content_hash": null, "message_id": null, "sent_at": null}, "409200061": {"chat_id": null, "content_hash": null, "message_id": null, "sent_at": null}, "409202061": {"chat_id": null, "content_hash": null, "message_id": null, "sent_at": null}, "409203061": {"chat_id": null, "content_hash": null, "message_id": null, "sent_at": null}, "409204061": {"chat_id": null, "content_hash": null, "message_id": null, "sent_at": null}, "409205061": {"chat_id": null, "content_hash": null, "message_id": null, "sent_at": null}, "409206061": {"chat_id": null, "content_hash": null, "message_id": null, "sent_at": null}, "409208061": {"chat_id": null, "content_hash": null, "message_id": null, "sent_at": null}, "409211061": {"chat_id": null, "content_hash": null, "message_id": null, "sent_at": null}, "409212061": {"chat_id": null, "content_hash": null, "message_id": null, "sent_at": null}, "409213061": {"chat_id": null, "content_hash": null, "message_id": null, "sent_at": null}, "409214061": {"chat_id": null, "content_hash": null, "message_id": null, "sent_at": null}, "409215061": {"chat_id": null, "content_hash": null, "message_id": null, "sent_at": null}, "409219061": {"chat_id": null, "content_hash": null, "message_id": null, "sent_at": null}, "409220061": {"chat_id": null, "content_hash": null, "message_id": null, "sent_at": null}, "409223061": {"chat_id": null, "content_hash": null, "message_id": null, "sent_at": null}, "409224061": {"chat_id": null, "content_hash": null, "message_id": null, "sent_at": null}, "409226061": {"chat_id": null, "content_hash": null, "message_id": null, "sent_at": null}, "409229061": {"chat_id": null, "content_hash": null, "message_id": null, "sent_at": null}, "409231061": {"chat_id": null, "content_hash": null, "message_id": null, "sent_at": null}, "409233061": {"chat_id": null, "content_hash": null, "message_id": null, "sent_at": null}, "409234061": {"chat_id": null, "content_hash": null, "message_id": null, "sent_at": null}, "409235061": {"chat_id": null, "content_hash": null, "message_id": null, "sent_at": null}, "409238061": {"chat_id": null, "content_hash": null, "message_id": null, "sent_at": null}, "409240061": {"chat_id": null, "content_hash": null, "message_id": null, "sent_at": null}, "409241061": {"chat_id": null, "content_hash": null, "message_id": null, "sent_at": null}, "409242061": {"chat_id": null, "content_hash": null, "message_id": null, "sent_at": null}, "409244061": {"chat_id": null, "content_hash": null, "message_id": null, "sent_at": null}, "409247061": {"chat_id": null, "content_hash": null, "message_id": null, "sent_at": null}, "409250061": {"chat_id": null, "content_hash": null, "message_id": null, "sent_at": null}, "409254061": {"chat_id": null, "content_hash": null, "message_id": null, "sent_at": null}, "409257061": {"chat_id": null, "content_hash": null, "message_id": null, "sent_at": null}, "409258061": {"chat_id": null, "content_hash": null, "message_id": null, "sent_at": null}, "409260061": {"chat_id": null, "content_hash": null, "message_id": null, "sent_at": null}, "409268061": {"chat_id": null, "content_hash": null, "message_id": null, "sent_at": null}, "409269061": {"chat_id": null, "content_hash": null, "message_id": null, "sent_at": null}, "409270061": {"chat_id": null, "content_hash": null, "message_id": null, "sent_at": null}, "409271061": {"chat_id": null, "content_hash": null, "message_id": null, "sent_at": null}, "409273061": {"chat_id": null, "content_hash": null, "message_id": null, "sent_at": null}, "409278061": {"chat_id": null, "content_hash": null, "message_id": null, "sent_at": null}, "409281061": {"chat_id": null, "content_hash": null, "message_id": null, "sent_at": null}, "409283061": {"chat_id": null, "content_hash": null, "message_id": null, "sent_at": null}, "409285061": {"chat_id": null, "content_hash": null, "message_id": null, "sent_at": null}, "409286061": {"chat_id": null, "content_hash": null, "message_id": null, "sent_at": null}, "409288061": {"chat_id": null, "content_hash": null, "message_id": null, "sent_at": null}, "409289061": {"chat_id": null, "content_hash": null, "message_id": null, "sent_at": null}, "409292061": {"chat_id": null, "content_hash": null, "message_id": null, "sent_at": null}, "409293061": {"chat_id": null, "content_hash": null, "message_id": null, "sent_at": null}, "409298061": {"chat_id": null, "content_hash": null, "message_id": null, "sent_at": null}, "409304061": {"chat_id": null, "content_hash": null, "message_id": null, "sent_at": null}, "409305061": {"chat_id": null, "content_hash": null, "message_id": null, "sent_at": null}, "409312061": {"chat_id": null, "content_hash": null, "message_id": null, "sent_at": null}, "409314061": {"chat_id": null, "content_hash": null, "message_id": null, "sent_at": null}, "409325061": {"chat_id": null, "content_hash": null, "message_id": null, "sent_at": null}, "409326061": {"chat_id": null, "content_hash": null, "message_id": null, "sent_at": null}, "409330061": {"chat_id": null, "content_hash": null, "message_id": null, "sent_at": null}, "409332061": {"chat_id": null, "content_hash": null, "message_id": null, "sent_at": null}, "409334061": {"chat_id": null, "content_hash": null, "message_id": null, "sent_at": null}, "409339061": {"chat_id": null, "content_hash": null, "message_id": null, "sent_at": null}, "409349061": {"chat_id": null, "content_hash": null, "message_id": null, "sent_at": null}, "409352061": {"chat_id": null, "content_hash": null, "message_id": null, "sent_at": null}, "409354061": {"chat_id": null, "content_hash": null, "message_id": null, "sent_at": null}, "409355061": {"chat_id": null, "content_hash": null, "message_id": null, "sent_at": null}, "409356061": {"chat_id": null, "content_hash": null, "message_id": null, "sent_at": null}, "409357061": {"chat_id": null, "content_hash": null, "message_id": null, "sent_at": null}, "409359061": {"chat_id": null, "content_hash": null, "message_id": null, "sent_at": null}, "409361061": {"chat_id": null, "content_hash": null, "message_id": null, "sent_at": null}, "409364061": {"chat_id": null, "content_hash": null, "message_id": null, "sent_at": null}, "409368061": {"chat_id": null, "content_hash": null, "message_id": null, "sent_at": null}, "409373061": {"chat_id": null, "content_hash": null, "message_id": null, "sent_at": null}, "409374061": {"chat_id": null, "content_hash": null, "message_id": null, "sent_at": null}, "409378061": {"chat_id": null, "content_hash": null, "message_id": null, "sent_at": null}, "409379061": {"chat_id": null, "content_hash": null, "message_id": null, "sent_at": null}, "409380061": {"chat_id": null, "content_hash": null, "message_id": null, "sent_at": null}, "409381061": {"chat_id": null, "content_hash": null, "message_id": null, "sent_at": null}, "409389061": {"chat_id": null, "content_hash": null, "message_id": null, "sent_at": null}, "409397061": {"chat_id": null, "content_hash": null, "message_id": null, "sent_at": null}, "409400061": {"chat_id": null, "content_hash": null, "message_id": null, "sent_at": null}, "409402061": {"chat_id": null, "content_hash": null, "message_id": null, "sent_at": null}, "409404061": {"chat_id": null, "content_hash": null, "message_id": null, "sent_at": null}, "409405061": {"chat_id": null, "content_hash": null, "message_id": null, "sent_at": null}, "409408061": {"chat_id": null, "content_hash": null, "message_id": null, "sent_at": null}, "409410061": {"chat_id": null, "content_hash": null, "message_id": null, "sent_at": null}, "409414061": {"chat_id": null, "content_hash": null, "message_id": null, "sent_at": null}, "409415061": {"chat_id": null, "content_hash": null, "message_id": null, "sent_at": null}, "409416061": {"chat_id": null, "content_hash": null, "message_id": null, "sent_at": null}, "409417061": {"chat_id": null, "content_hash": null, "message_id": null, "sent_at": null}, "409418061": {"chat_id": null, "content_hash": null, "message_id": null, "sent_at": null}, "409428061": {"chat_id": null, "content_hash": null, "message_id": null, "sent_at": null}, "409435061": {"chat_id": null, "content_hash": null, "message_id": null, "sent_at": null}, "409440061": {"chat_id": null, "content_hash": null, "message_id": null, "sent_at": null}, "409442061": {"chat_id": null, "content_hash": null, "message_id": null, "sent_at": null}, "409443061": {"chat_id": null, "content_hash": null, "message_id": null, "sent_at": null}, "409448061": {"chat_id": null, "content_hash": null, "message_id": null, "sent_at": null}, "409449061": {"chat_id": null, "content_hash": null, "message_id": null, "sent_at": null}, "409451061": {"chat_id": null, "content_hash": null, "message_id": null, "sent_at": null}, "409452061": {"chat_id": null, "content_hash": null, "message_id": null, "sent_at": null}, "409453061": {"chat_id": null, "content_hash": null, "message_id": null, "sent_at": null}, "409455061": {"chat_id": null, "content_hash": null, "message_id": null, "sent_at": null}, "409457061": {"chat_id": null, "content_hash": null, "message_id": null, "sent_at": null}, "409458061": {"chat_id": null, "content_hash": null, "message_id": null, "sent_at": null}, "409459061": {"chat_id": null, "content_hash": null, "message_id": null, "sent_at": null}, "409465061": {"chat_id": null, "content_hash": null, "message_id": null, "sent_at": null}, "409468061": {"chat_id": null, "content_hash": null, "message_id": null, "sent_at": null}, "409469061": {"chat_id": null, "content_hash": null, "message_id": null, "sent_at": null}, "409472061": {"chat_id": null, "content_hash": null, "message_id": null, "sent_at": null}, "409473061": {"chat_id": null, "content_hash": null, "message_id": null, "sent_at": null}, "409474061": {"chat_id": null, "content_hash": null, "message_id": null, "sent_at": null}, "409476061": {"chat_id": null, "content_hash": null, "message_id": null, "sent_at": null}, "409477061": {"chat_id": null, "content_hash": null, "message_id": null, "sent_at": null}, "409478061": {"chat_id": null, "content_hash": null, "message_id": null, "sent_at": null}, "409479061": {"chat_id": null, "content_hash": null, "message_id": null, "sent_at": null}, "409481061": {"chat_id": null, "content_hash": null, "message_id": null, "sent_at": null}, "409483061": {"chat_id": null, "content_hash": null, "message_id": null, "sent_at": null}, "409485061": {"chat_id": null, "content_hash": null, "message_id": null, "sent_at": null}, "409488061": {"chat_id": null, "content_hash": null, "message_id": null, "sent_at": null}, "409491061": {"chat_id": null, "content_hash": null, "message_id": null, "sent_at": null}, "409492061": {"chat_id": null, "content_hash": null, "message_id": null, "sent_at": null}, "409493061": {"chat_id": null, "content_hash": null, "message_id": null, "sent_at": null}, "409494061": {"chat_id": null, "content_hash": null, "message_id": null, "sent_at": null}, "409496061": {"chat_id": null, "content_hash": null, "message_id": null, "sent_at": null}, "409497061": {"chat_id": null, "content_hash": null, "message_id": null, "sent_at": null}, "409499061": {"chat_id": null, "content_hash": null, "message_id": null, "sent_at": null}, "409500061": {"chat_id": null, "content_hash": null, "message_id": null, "sent_at": null}, "409501061": {"chat_id": null, "content_hash": null, "message_id": null, "sent_at": null}, "409503061": {"chat_id": null, "content_hash": null, "message_id": null, "sent_at": null}, "409506061": {"chat_id": null, "content_hash": null, "message_id": null, "sent_at": null}, "409509061": {"chat_id": null, "content_hash": null, "message_id": null, "sent_at": null}, "409510061": {"chat_id": null, "content_hash": null, "message_id": null, "sent_at": null}, "409511061": {"chat_id": null, "content_hash": null, "message_id": null, "sent_at": null}, "409512061": {"chat_id": null, "content_hash": null, "message_id": null, "sent_at": null}, "409513061": {"chat_id": null, "content_hash": null, "message_id": null, "sent_at": null}, "409518061": {"chat_id": null, "content_hash": null, "message_id": null, "sent_at": null}, "409522061": {"chat_id": null, "content_hash": null, "message_id": null, "sent_at": null}, "409527061": {"chat_id": null, "content_hash": null, "message_id": null, "sent_at": null}, "409533061": {"chat_id": null, "content_hash": null, "message_id": null, "sent_at": null}, "409534061": {"chat_id": null, "content_hash": null, "message_id": null, "sent_at": null}, "409536061": {"chat_id": null, "content_hash": null, "message_id": null, "sent_at": null}, "409537061": {"chat_id": null, "content_hash": null, "message_id": null, "sent_at": null}, "409538061": {"chat_id": null, "content_hash": null, "message_id": null, "sent_at": null}, "409540061": {"chat_id": null, "content_hash": null, "message_id": null, "sent_at": null}, "409541061": {"chat_id": null, "content_hash": null, "message_id": null, "sent_at": null}, "409542061": {"chat_id": null, "content_hash": null, "message_id": null, "sent_at": null}, "409543061": {"chat_id": null, "content_hash": null, "message_id": null, "sent_at": null}, "409544061": {"chat_id": null, "content_hash": null, "message_id": null, "sent_at": null}, "409545061": {"chat_id": null, "content_hash": null, "message_id": null, "sent_at": null}, "409546061": {"chat_id": null, "content_hash": null, "message_id": null, "sent_at": null}, "409550061": {"chat_id": null, "content_hash": null, "message_id": null, "sent_at": null}, "409552061": {"chat_id": null, "content_hash": null, "message_id": null, "sent_at": null}, "409554061": {"chat_id": null, "content_hash": null, "message_id": null, "sent_at": null}, "409556061": {"chat_id": null, "content_hash": null, "message_id": null, "sent_at": null}, "409559061": {"chat_id": null, "content_hash": null, "message_id": null, "sent_at": null}, "409561061": {"chat_id": null, "content_hash": null, "message_id": null, "sent_at": null}, "409562061": {"chat_id": null, "content_hash": null, "message_id": null, "sent_at": null}, "409566061": {"chat_id": null, "content_hash": null, "message_id": null, "sent_at": null}, "409567061": {"chat_id": null, "content_hash": null, "message_id": null, "sent_at": null}, "409570061": {"chat_id": null, "content_hash": null, "message_id": null, "sent_at": null}, "409571061": {"chat_id": null, "content_hash": null, "message_id": null, "sent_at": null}, "409572061": {"chat_id": null, "content_hash": null, "message_id": null, "sent_at": null}, "409573061": {"chat_id": null, "content_hash": null, "message_id": null, "sent_at": null}, "409574061": {"chat_id": null, "content_hash": null, "message_id": null, "sent_at": null}, "409575061": {"chat_id": null, "content_hash": null, "message_id": null, "sent_at": null}, "409576061": {"chat_id": null, "content_hash": null, "message_id": null, "sent_at": null}, "409578061": {"chat_id": null, "content_hash": null, "message_id": null, "sent_at": null}, "409579061": {"chat_id": null, "content_hash": null, "message_id": null, "sent_at": null}, "409580061": {"chat_id": null, "content_hash": null, "message_id": null, "sent_at": null}, "409581061": {"chat_id": null, "content_hash": null, "message_id": null, "sent_at": null}, "409582061": {"chat_id": null, "content_hash": null, "message_id": null, "sent_at": null}, "409583061": {"chat_id": null, "content_hash": null, "message_id": null, "sent_at": null}, "409588061": {"chat_id": null, "content_hash": null, "message_id": null, "sent_at": null}, "409590061": {"chat_id": null, "content_hash": null, "message_id": null, "sent_at": null}, "409592061": {"chat_id": null, "content_hash": null, "message_id": null, "sent_at": null}, "409601061": {"chat_id": null, "content_hash": null, "message_id": null, "sent_at": null}, "409605061": {"chat_id": null, "content_hash": null, "message_id": null, "sent_at": null}, "409612061": {"chat_id": null, "content_hash": null, "message_id": null, "sent_at": null}, "409625061": {"chat_id": null, "content_hash": null, "message_id": null, "sent_at": null}, "409628061": {"chat_id": null, "content_hash": null, "message_id": null, "sent_at": null}, "409631061": {"chat_id": null, "content_hash": null, "message_id": null, "sent_at": null}, "409633061": {"chat_id": null, "content_hash": null, "message_id": null, "sent_at": null}, "409638061": {"chat_id": null, "content_hash": null, "message_id": null, "sent_at": null}, "409639061": {"chat_id": null, "content_hash": null, "message_id": null, "sent_at": null}, "409642061": {"chat_id": null, "content_hash": null, "message_id": null, "sent_at": null}, "409645061": {"chat_id": null, "content_hash": null, "message_id": null, "sent_at": null}, "409650061": {"chat_id": null, "content_hash": null, "message_id": null, "sent_at": null}, "409651061": {"chat_id": null, "content_hash": null, "message_id": null, "sent_at": null}, "409655061": {"chat_id": null, "content_hash": null, "message_id": null, "sent_at": null}, "409656061": {"chat_id": null, "content_hash": null, "message_id": null, "sent_at": null}, "409657061": {"chat_id": null, "content_hash": null, "message_id": null, "sent_at": null}, "409660061": {"chat_id": null, "content_hash": null, "message_id": null, "sent_at": null}, "409661061": {"chat_id": null, "content_hash": null, "message_id": null, "sent_at": null}, "409662061": {"chat_id": null, "content_hash": null, "message_id": null, "sent_at": null}, "409664061": {"chat_id": null, "content_hash": null, "message_id": null, "sent_at": null}, "409665061": {"chat_id": null, "content_hash": null, "message_id": null, "sent_at": null}, "409666061": {"chat_id": null, "content_hash": null, "message_id": null, "sent_at": null}, "409672061": {"chat_id": null, "content_hash": null, "message_id": null, "sent_at": null}, "409673061": {"chat_id": null, "content_hash": null, "message_id": null, "sent_at": null}, "409681061": {"chat_id": null, "content_hash": null, "message_id": null, "sent_at": null}, "409683061": {"chat_id": null, "content_hash": null, "message_id": null, "sent_at": null}, "409690061": {"chat_id": null, "content_hash": null, "message_id": null, "sent_at": null}, "409691061": {"chat_id": null, "content_hash": null, "message_id": null, "sent_at": null}, "409696061": {"chat_id": null, "content_hash": null, "message_id": null, "sent_at": null}, "409704061": {"chat_id": null, "content_hash": null, "message_id": null, "sent_at": null}, "409705061": {"chat_id": null, "content_hash": null, "message_id": null, "sent_at": null}, "409714061": {"chat_id": null, "content_hash": null, "message_id": null, "sent_at": null}, "409721061": {"chat_id": null, "content_hash": null, "message_id": null, "sent_at": null}, "409722061": {"chat_id": null, "content_hash": null, "message_id": null, "sent_at": null}, "409723061": {"chat_id": null, "content_hash": null, "message_id": null, "sent_at": null}, "409726061": {"chat_id": null, "content_hash": null, "message_id": null, "sent_at": null}, "409728061": {"chat_id": null, "content_hash": null, "message_id": null, "sent_at": null}, "409729061": {"chat_id": null, "content_hash": null, "message_id": null, "sent_at": null}, "409733061": {"chat_id": null, "content_hash": null, "message_id": null, "sent_at": null}, "409735061": {"chat_id": null, "content_hash": null, "message_id": null, "sent_at": null}, "409739061": {"chat_id": null, "content_hash": null, "message_id": null, "sent_at": null}, "409745061": {"chat_id": null, "content_hash": null, "message_id": null, "sent_at": null}, "409747061": {"chat_id": null, "content_hash": null, "message_id": null, "sent_at": null}, "409749061": {"chat_id": null, "content_hash": null, "message_id": null, "sent_at": null}, "409750061": {"chat_id": null, "content_hash": null, "message_id": null, "sent_at": null}, "409751061": {"chat_id": null, "content_hash": null, "message_id": null, "sent_at": null}, "409752061": {"chat_id": null, "content_hash": null, "message_id": null, "sent_at": null}, "409753061": {"chat_id": null, "content_hash": null, "message_id": null, "sent_at": null}, "409755061": {"chat_id": null, "content_hash": null, "message_id": null, "sent_at": null}, "409757061": {"chat_id": null, "content_hash": null, "message_id": null, "sent_at": null}, "409758061": {"chat_id": null, "content_hash": null, "message_id": null, "sent_at": null}, "409760061": {"chat_id": null, "content_hash": null, "message_id": null, "sent_at": null}, "409761061": {"chat_id": null, "content_hash": null, "message_id": null, "sent_at": null}, "409763061": {"chat_id": null, "content_hash": null, "message_id": null, "sent_at": null}, "409764061": {"chat_id": null, "content_hash": null, "message_id": null, "sent_at": null}, "409766061": {"chat_id": null, "content_hash": null, "message_id": null, "sent_at": null}, "409767061": {"chat_id": null, "content_hash": null, "message_id": null, "sent_at": null}, "409771061": {"chat_id": null, "content_hash": null, "message_id": null, "sent_at": null}, "409773061": {"chat_id": null, "content_hash": null, "message_id": null, "sent_at": null}, "409777061": {"chat_id": null, "content_hash": null, "message_id": null, "sent_at": null}, "409778061": {"chat_id": null, "content_hash": null, "message_id": null, "sent_at": null}, "409779061": {"chat_id": null, "content_hash": null, "message_id": null, "sent_at": null}, "409785061": {"chat_id": null, "content_hash": null, "message_id": null, "sent_at": null}, "409786061": {"chat_id": null, "content_hash": null, "message_id": null, "sent_at": null}, "409787061": {"chat_id": null, "content_hash": null, "message_id": null, "sent_at": null}, "409788061": {"chat_id": null, "content_hash": null, "message_id": null, "sent_at": null}, "409789061": {"chat_id": null, "content_hash": null, "message_id": null, "sent_at": null}, "409792061": {"chat_id": null, "content_hash": null, "message_id": null, "sent_at": null}, "409793061": {"chat_id": null, "content_hash": null, "message_id": null, "sent_at": null}, "409794061": {"chat_id": null, "content_hash": null, "message_id": null, "sent_at": null}, "409796061": {"chat_id": null, "content_hash": null, "message_id": null, "sent_at": null}, "409797061": {"chat_id": null, "content_hash": null, "message_id": null, "sent_at": null}, "409800061": {"chat_id": null, "content_hash": null, "message_id": null, "sent_at": null}, "409801061": {"chat_id": null, "content_hash": null, "message_id": null, "sent_at": null}, "409802061": {"chat_id": null, "content_hash": null, "message_id": null, "sent_at": null}, "409805061": {"chat_id": null, "content_hash": null, "message_id": null, "sent_at": null}, "409806061": {"chat_id": null, "content_hash": null, "message_id": null, "sent_at": null}, "409807061": {"chat_id": null, "content_hash": null, "message_id": null, "sent_at": null}, "409808061": {"chat_id": null, "content_hash": null, "message_id": null, "sent_at": null}, "409809061": {"chat_id": null, "content_hash": null, "message_id": null, "sent_at": null}, "409810061": {"chat_id": null, "content_hash": null, "message_id": null, "sent_at": null}, "409811061": {"chat_id": null, "content_hash": null, "message_id": null, "sent_at": null}, "409814061": {"chat_id": null, "content_hash": null, "message_id": null, "sent_at": null}, "409815061": {"chat_id": null, "content_hash": null, "message_id": null, "sent_at": null}, "409820061": {"chat_id": null, "content_hash": null, "message_id": null, "sent_at": null}, "409821061": {"chat_id": null, "content_hash": null, "message_id": null, "sent_at": null}, "409822061": {"chat_id": null, "content_hash": null, "message_id": null, "sent_at": null}, "409823061": {"chat_id": null, "content_hash": null, "message_id": null, "sent_at": null}, "409828061": {"chat_id": null, "content_hash": null, "message_id": null, "sent_at": null}, "409830061": {"chat_id": null, "content_hash": null, "message_id": null, "sent_at": null}, "409831061": {"chat_id": null, "content_hash": null, "message_id": null, "sent_at": null}, "409833061": {"chat_id": null, "content_hash": null, "message_id": null, "sent_at": null}, "409834061": {"chat_id": null, "content_hash": null, "message_id": null, "sent_at": null}, "409835061": {"chat_id": null, "content_hash": null, "message_id": null, "sent_at": null}, "409839061": {"chat_id": null, "content_hash": null, "message_id": null, "sent_at": null}, "409840061": {"chat_id": null, "content_hash": null, "message_id": null, "sent_at": null}, "409842061": {"chat_id": null, "content_hash": null, "message_id": null, "sent_at": null}, "409843061": {"chat_id": null, "content_hash": null, "message_id": null, "sent_at": null}, "409845061": {"chat_id": null, "content_hash": null, "message_id": null, "sent_at": null}, "409847061": {"chat_id": null, "content_hash": null, "message_id": null, "sent_at": null}, "409848061": {"chat_id": null, "content_hash": null, "message_id": null, "sent_at": null}, "409850061": {"chat_id": null, "content_hash": null, "message_id": null, "sent_at": null}, "409853061": {"chat_id": null, "content_hash": null, "message_id": null, "sent_at": null}, "409863061": {"chat_id": null, "content_hash": null, "message_id": null, "sent_at": null}, "409864061": {"chat_id": null, "content_hash": null, "message_id": null, "sent_at": null}, "409865061": {"chat_id": null, "content_hash": null, "message_id": null, "sent_at": null}, "409866061": {"chat_id": null, "content_hash": null, "message_id": null, "sent_at": null}, "409867061": {"chat_id": null, "content_hash": null, "message_id": null, "sent_at": null}, "409868061": {"chat_id": null, "content_hash": null, "message_id": null, "sent_at": null}, "409869061": {"chat_id": null, "content_hash": null, "message_id": null, "sent_at": null}, "409870061": {"chat_id": null, "content_hash": null, "message_id": null, "sent_at": null}, "409872061": {"chat_id": null, "content_hash": null, "message_id": null, "sent_at": null}, "409873061": {"chat_id": null, "content_hash": null, "message_id": null, "sent_at": null}, "409876061": {"chat_id": null, "content_hash": null, "message_id": null, "sent_at": null}, "409877061": {"chat_id": null, "content_hash": null, "message_id": null, "sent_at": null}, "409880061": {"chat_id": null, "content_hash": null, "message_id": null, "sent_at": null}, "409882061": {"chat_id": null, "content_hash": null, "message_id": null, "sent_at": null}, "409883061": {"chat_id": null, "content_hash": null, "message_id": null, "sent_at": null}, "409889061": {"chat_id": null, "content_hash": null, "message_id": null, "sent_at": null}, "409893061": {"chat_id": null, "content_hash": null, "message_id": null, "sent_at": null}, "409899061": {"chat_id": null, "content_hash": null, "message_id": null, "sent_at": null}, "409900061": {"chat_id": null, "content_hash": null, "message_id": null, "sent_at": null}, "409904061": {"chat_id": null, "content_hash": null, "message_id": null, "sent_at": null}, "409906061": {"chat_id": null, "content_hash": null, "message_id": null, "sent_at": null}, "409907061": {"chat_id": null, "content_hash": null, "message_id": null, "sent_at": null}, "409913061": {"chat_id": null, "content_hash": null, "message_id": null, "sent_at": null}, "409914061": {"chat_id": null, "content_hash": null, "message_id": null, "sent_at": null}, "409915061": {"chat_id": null, "content_hash": null, "message_id": null, "sent_at": null}, "409916061": {"chat_id": null, "content_hash": null, "message_id": null, "sent_at": null}, "409920061": {"chat_id": null, "content_hash": null, "message_id": null, "sent_at": null}, "409929061": {"chat_id": null, "content_hash": null, "message_id": null, "sent_at": null}, "409932061": {"chat_id": null, "content_hash": null, "message_id": null, "sent_at": null}, "409933061": {"chat_id": null, "content_hash": null, "message_id": null, "sent_at": null}, "409935061": {"chat_id": null, "content_hash": null, "message_id": null, "sent_at": null}, "409936061": {"chat_id": null, "content_hash": null, "message_id": null, "sent_at": null}, "409941061": {"chat_id": null, "content_hash": null, "message_id": null, "sent_at": null}, "409947061": {"chat_id": null, "content_hash": null, "message_id": null, "sent_at": null}, "409949061": {"chat_id": null, "content_hash": null, "message_id": null, "sent_at": null}, "409950061": {"chat_id": null, "content_hash": null, "message_id": null, "sent_at": null}, "409952061": {"chat_id": null, "content_hash": null, "message_id": null, "sent_at": null}, "409953061": {"chat_id": null, "content_hash": null, "message_id": null, "sent_at": null}, "409958061": {"chat_id": null, "content_hash": null, "message_id": null, "sent_at": null}, "409960061": {"chat_id": null, "content_hash": null, "message_id": null, "sent_at": null}, "409963061": {"chat_id": null, "content_hash": null, "message_id": null, "sent_at": null}, "409965061": {"chat_id": null, "content_hash": null, "message_id": null, "sent_at": null}, "409966061": {"chat_id": null, "content_hash": null, "message_id": null, "sent_at": null}, "409967061": {"chat_id": null, "content_hash": null, "message_id": null, "sent_at": null}, "409968061": {"chat_id": null, "content_hash": null, "message_id": null, "sent_at": null}, "409969061": {"chat_id": null, "content_hash": null, "message_id": null, "sent_at": null}, "409971061": {"chat_id": null, "content_hash": null, "message_id": null, "sent_at": null}, "409972061": {"chat_id": null, "content_hash": null, "message_id": null, "sent_at": null}, "409975061": {"chat_id": null, "content_hash": null, "message_id": null, "sent_at": null}, "409977061": {"chat_id": null, "content_hash": null, "message_id": null, "sent_at": null}, "409979061": {"chat_id": null, "content_hash": null, "message_id": null, "sent_at": null}, "409980061": {"chat_id": null, "content_hash": null, "message_id": null, "sent_at": null}, "409984061": {"chat_id": null, "content_hash": null, "message_id": null, "sent_at": null}, "409985061": {"chat_id": null, "content_hash": null, "message_id": null, "sent_at": null}, "409992061": {"chat_id": null, "content_hash": null, "message_id": null, "sent_at": null}, "409994061": {"chat_id": null, "content_hash": null, "message_id": null, "sent_at": null}, "409995061": {"chat_id": null, "content_hash": null, "message_id": null, "sent_at": null}, "410000061": {"chat_id": null, "content_hash": null, "message_id": null, "sent_at": null}, "410001061": {"chat_id": null, "content_hash": null, "message_id": null, "sent_at": null}, "410004061": {"chat_id": null, "content_hash": null, "message_id": null, "sent_at": null}, "410005061": {"chat_id": null, "content_hash": null, "message_id": null, "sent_at": null}, "410006061": {"chat_id": null, "content_hash": null, "message_id": null, "sent_at": null}, "410007061": {"chat_id": null, "content_hash": null, "message_id": null, "sent_at": null}, "410009061": {"chat_id": null, "content_hash": null, "message_id": null, "sent_at": null}, "410012061": {"chat_id": null, "content_hash": null, "message_id": null, "sent_at": null}, "410013061": {"chat_id": null, "content_hash": null, "message_id": null, "sent_at": null}, "410014061": {"chat_id": null, "content_hash": null, "message_id": null, "sent_at": null}, "410017061": {"chat_id": null, "content_hash": null, "message_id": null, "sent_at": null}, "410019061": {"chat_id": null, "content_hash": null, "message_id": null, "sent_at": null}, "410020061": {"chat_id": null, "content_hash": null, "message_id": null, "sent_at": null}, "410021061": {"chat_id": null, "content_hash": null, "message_id": null, "sent_at": null}, "410024061": {"chat_id": null, "content_hash": null, "message_id": null, "sent_at": null}, "410026061": {"chat_id": null, "content_hash": null, "message_id": null, "sent_at": null}, "410028061": {"chat_id": null, "content_hash": null, "message_id": null, "sent_at": null}, "410037061": {"chat_id": null, "content_hash": null, "message_id": null, "sent_at": null}, "410038061": {"chat_id": null, "content_hash": null, "message_id": null, "sent_at": null}, "410042061": {"chat_id": null, "content_hash": null, "message_id": null, "sent_at": null}, "410044061": {"chat_id": null, "content_hash": null, "message_id": null, "sent_at": null}, "410045061": {"chat_id": null, "content_hash": null, "message_id": null, "sent_at": null}, "410048061": {"chat_id": null, "content_hash": null, "message_id": null, "sent_at": null}, "410049061": {"chat_id": null, "content_hash": null, "message_id": null, "sent_at": null}, "410050061": {"chat_id": null, "content_hash": null, "message_id": null, "sent_at": null}, "410052061": {"chat_id": null, "content_hash": null, "message_id": null, "sent_at": null}, "410054061": {"chat_id": null, "content_hash": null, "message_id": null, "sent_at": null}, "410055061": {"chat_id": null, "content_hash": null, "message_id": null, "sent_at": null}, "410057061": {"chat_id": null, "content_hash": null, "message_id": null, "sent_at": null}, "410058061": {"chat_id": null, "content_hash": null, "message_id": null, "sent_at": null}, "410059061": {"chat_id": null, "content_hash": null, "message_id": null, "sent_at": null}, "410060061": {"chat_id": null, "content_hash": null, "message_id": null, "sent_at": null}, "410061061": {"chat_id": null, "content_hash": null, "message_id": null, "sent_at": null}, "410062061": {"chat_id": null, "content_hash": null, "message_id": null, "sent_at": null}, "410063061": {"chat_id": null, "content_hash": null, "message_id": null, "sent_at": null}, "410064061": {"chat_id": null, "content_hash": null, "message_id": null, "sent_at": null}, "410066061": {"chat_id": null, "content_hash": null, "message_id": null, "sent_at": null}, "410067061": {"chat_id": null, "content_hash": null, "message_id": null, "sent_at": null}, "410073061": {"chat_id": null, "content_hash": null, "message_id": null, "sent_at": null}, "410081061": {"chat_id": null, "content_hash": null, "message_id": null, "sent_at": null}, "410102061": {"chat_id": null, "content_hash": null, "message_id": null, "sent_at": null}, "410110061": {"chat_id": null, "content_hash": null, "message_id": null, "sent_at": null}, "410111061": {"chat_id": null, "content_hash": null, "message_id": null, "sent_at": null}, "410112061": {"chat_id": null, "content_hash": null, "message_id": null, "sent_at": null}, "410113061": {"chat_id": null, "content_hash": null, "message_id": null, "sent_at": null}, "410114061": {"chat_id": null, "content_hash": null, "message_id": null, "sent_at": null}, "410125061": {"chat_id": null, "content_hash": null, "message_id": null, "sent_at": null}, "410127061": {"chat_id": null, "content_hash": null, "message_id": null, "sent_at": null}, "410129061": {"chat_id": null, "content_hash": null, "message_id": null, "sent_at": null}, "410133061": {"chat_id": null, "content_hash": null, "message_id": null, "sent_at": null}, "410134061": {"chat_id": null, "content_hash": null, "message_id": null, "sent_at": null}, "410138061": {"chat_id": null, "content_hash": null, "message_id": null, "sent_at": null}, "410139061": {"chat_id": null, "content_hash": null, "message_id": null, "sent_at": null}, "410141061": {"chat_id": null, "content_hash": null, "message_id": null, "sent_at": null}, "410142061": {"chat_id": null, "content_hash": null, "message_id": null, "sent_at": null}, "410143061": {"chat_id": null, "content_hash": null, "message_id": null, "sent_at": null}, "410144061": {"chat_id": null, "content_hash": null, "message_id": null, "sent_at": null}, "410145061": {"chat_id": null, "content_hash": null, "message_id": null, "sent_at": null}, "410146061": {"chat_id": null, "content_hash": null, "message_id": null, "sent_at": null}, "410147061": {"chat_id": null, "content_hash": null, "message_id": null, "sent_at": null}, "410149061": {"chat_id": null, "content_hash": null, "message_id": null, "sent_at": null}, "410152061": {"chat_id": null, "content_hash": null, "message_id": null, "sent_at": null}, "410154061": {"chat_id": null, "content_hash": null, "message_id": null, "sent_at": null}, "410158061": {"chat_id": null, "content_hash": null, "message_id": null, "sent_at": null}, "410159061": {"chat_id": null, "content_hash": null, "message_id": null, "sent_at": null}, "410160061": {"chat_id": null, "content_hash": null, "message_id": null, "sent_at": null}, "410161061": {"chat_id": null, "content_hash": null, "message_id": null, "sent_at": null}, "410165061": {"chat_id": null, "content_hash": null, "message_id": null, "sent_at": null}, "410168061": {"chat_id": null, "content_hash": null, "message_id": null, "sent_at": null}, "410170061": {"chat_id": null, "content_hash": null, "message_id": null, "sent_at": null}, "410174061": {"chat_id": null, "content_hash": null, "message_id": null, "sent_at": null}, "410176061": {"chat_id": null, "content_hash": null, "message_id": null, "sent_at": null}, "410178061": {"chat_id": null, "content_hash": null, "message_id": null, "sent_at": null}, "410180061": {"chat_id": null, "content_hash": null, "message_id": null, "sent_at": null}, "410182061": {"chat_id": null, "content_hash": null, "message_id": null, "sent_at": null}, "410186061": {"chat_id": null, "content_hash": null, "message_id": null, "sent_at": null}, "410187061": {"chat_id": null, "content_hash": null, "message_id": null, "sent_at": null}, "410192061": {"chat_id": null, "content_hash": null, "message_id": null, "sent_at": null}, "410194061": {"chat_id": null, "content_hash": null, "message_id": null, "sent_at": null}, "410197061": {"chat_id": null, "content_hash": null, "message_id": null, "sent_at": null}, "410198061": {"chat_id": null, "content_hash": null, "message_id": null, "sent_at": null}, "410199061": {"chat_id": null, "content_hash": null, "message_id": null, "sent_at": null}, "410200061": {"chat_id": null, "content_hash": null, "message_id": null, "sent_at": null}, "410202061": {"chat_id": null, "content_hash": null, "message_id": null, "sent_at": null}, "410203061": {"chat_id": null, "content_hash": null, "message_id": null, "sent_at": null}, "410204061": {"chat_id": null, "content_hash": null, "message_id": null, "sent_at": null}, "410205061": {"chat_id": null, "content_hash": null, "message_id": null, "sent_at": null}, "410206061": {"chat_id": null, "content_hash": null, "message_id": null, "sent_at": null}, "410207061": {"chat_id": null, "content_hash": null, "message_id": null, "sent_at": null}, "410208061": {"chat_id": null, "content_hash": null, "message_id": null, "sent_at": null}, "410210061": {"chat_id": null, "content_hash": null, "message_id": null, "sent_at": null}, "410212061": {"chat_id": null, "content_hash": null, "message_id": null, "sent_at": null}, "410213061": {"chat_id": null, "content_hash": null, "message_id": null, "sent_at": null}, "410214061": {"chat_id": null, "content_hash": null, "message_id": null, "sent_at": null}, "410217061": {"chat_id": null, "content_hash": null, "message_id": null, "sent_at": null}, "410219061": {"chat_id": null, "content_hash": null, "message_id": null, "sent_at": null}, "410221061": {"chat_id": null, "content_hash": null, "message_id": null, "sent_at": null}, "410222061": {"chat_id": null, "content_hash": null, "message_id": null, "sent_at": null}, "410223061": {"chat_id": null, "content_hash": null, "message_id": null, "sent_at": null}, "410224061": {"chat_id": null, "content_hash": null, "message_id": null, "sent_at": null}, "410225061": {"chat_id": null, "content_hash": null, "message_id": null, "sent_at": null}, "410228061": {"chat_id": null, "content_hash": null, "message_id": null, "sent_at": null}, "410233061": {"chat_id": null, "content_hash": null, "message_id": null, "sent_at": null}, "410234061": {"chat_id": null, "content_hash": null, "message_id": null, "sent_at": null}, "410235061": {"chat_id": null, "content_hash": null, "message_id": null, "sent_at": null}, "410236061": {"chat_id": null, "content_hash": null, "message_id": null, "sent_at": null}, "410242061": {"chat_id": null, "content_hash": null, "message_id": null, "sent_at": null}, "410248061": {"chat_id": null, "content_hash": null, "message_id": null, "sent_at": null}, "410252061": {"chat_id": null, "content_hash": null, "message_id": null, "sent_at": null}, "410267061": {"chat_id": null, "content_hash": null, "message_id": null, "sent_at": null}, "410272061": {"chat_id": null, "content_hash": null, "message_id": null, "sent_at": null}, "410274061": {"chat_id": null, "content_hash": null, "message_id": null, "sent_at": null}, "410277061": {"chat_id": null, "content_hash": null, "message_id": null, "sent_at": null}, "410278061": {"chat_id": null, "content_hash": null, "message_id": null, "sent_at": null}, "410279061": {"chat_id": null, "content_hash": null, "message_id": null, "sent_at": null}, "410280061": {"chat_id": null, "content_hash": null, "message_id": null, "sent_at": null}, "410281061": {"chat_id": null, "content_hash": null, "message_id": null, "sent_at": null}, "410282061": {"chat_id": null, "content_hash": null, "message_id": null, "sent_at": null}, "410283061": {"chat_id": null, "content_hash": null, "message_id": null, "sent_at": null}, "410284061": {"chat_id": null, "content_hash": null, "message_id": null, "sent_at": null}, "410286061": {"chat_id": null, "content_hash": null, "message_id": null, "sent_at": null}, "410287061": {"chat_id": null, "content_hash": null, "message_id": null, "sent_at": null}, "410292061": {"chat_id": null, "content_hash": null, "message_id": null, "sent_at": null}, "410299061": {"chat_id": null, "content_hash": null, "message_id": null, "sent_at": null}, "410300061": {"chat_id": null, "content_hash": null, "message_id": null, "sent_at": null}, "410307061": {"chat_id": null, "content_hash": null, "message_id": null, "sent_at": null}, "410308061": {"chat_id": null, "content_hash": null, "message_id": null, "sent_at": null}, "410309061": {"chat_id": null, "content_hash": null, "message_id": null, "sent_at": null}, "410311061": {"chat_id": null, "content_hash": null, "message_id": null, "sent_at": null}, "410312061": {"chat_id": null, "content_hash": null, "message_id": null, "sent_at": null}, "413540061": {"chat_id": "-1003764354655", "content_hash": "d32f9053fd2c", "message_id": 2157, "sent_at": "2026-06-24T16:16:11+00:00"}, "413544061": {"chat_id": "-1003764354655", "content_hash": "7c9895a82d40", "message_id": 2134, "sent_at": "2026-06-24T06:31:32+00:00"}, "413547061": {"chat_id": "-1003764354655", "content_hash": "a6d96ff3cdc6", "message_id": 2135, "sent_at": "2026-06-24T07:01:32+00:00"}, "413549061": {"chat_id": "-1003764354655", "content_hash": "f21ad325bff4", "message_id": 2136, "sent_at": "2026-06-24T07:01:32+00:00"}, "413550061": {"chat_id": "-1003764354655", "content_hash": "0b5f82d0d16e", "message_id": 2137, "sent_at": "2026-06-24T07:01:32+00:00"}, "413551061": {"chat_id": "-1003764354655", "content_hash": "04ce3ac4731c", "message_id": 2138, "sent_at": "2026-06-24T07:01:32+00:00"}, "413552061": {"chat_id": "-1003764354655", "content_hash": "2d4dd64c04b3", "message_id": 2139, "sent_at": "2026-06-24T07:01:32+00:00"}, "413555061": {"chat_id": "-1003764354655", "content_hash": "18f8ee397361", "message_id": 2140, "sent_at": "2026-06-24T07:16:18+00:00"}, "413556061": {"chat_id": "-1003764354655", "content_hash": "b677580aa9ff", "message_id": 2141, "sent_at": "2026-06-24T07:46:07+00:00"}, "413558061": {"chat_id": "-1003764354655", "content_hash": "f37954051724", "message_id": 2142, "sent_at": "2026-06-24T08:01:35+00:00"}, "413561061": {"chat_id": "-1003764354655", "content_hash": "24fff2c00a20", "message_id": 2143, "sent_at": "2026-06-24T08:01:35+00:00"}, "413562061": {"chat_id": "-1003764354655", "content_hash": "45dd16739717", "message_id": 2144, "sent_at": "2026-06-24T08:16:13+00:00"}, "413563061": {"chat_id": "-1003764354655", "content_hash": "54bcb87a5111", "message_id": 2145, "sent_at": "2026-06-24T08:46:10+00:00"}, "413564061": {"chat_id": "-1003764354655", "content_hash": "772bea4b54f9", "message_id": 2146, "sent_at": "2026-06-24T08:46:10+00:00"}, "413572061": {"chat_id": "-1003764354655", "content_hash": "5a854382e50e", "message_id": 2147, "sent_at": "2026-06-24T10:16:09+00:00"}, "413573061": {"chat_id": "-1003764354655", "content_hash": "9a918dd5211c", "message_id": 2148, "sent_at": "2026-06-24T10:46:16+00:00"}, "413575061": {"chat_id": "-1003764354655", "content_hash": "80db1b323ca9", "message_id": 2149, "sent_at": "2026-06-24T11:01:46+00:00"}, "413577061": {"chat_id": "-1003764354655", "content_hash": "5a01be407362", "message_id": 2150, "sent_at": "2026-06-24T13:46:13+00:00"}, "413579061": {"chat_id": "-1003764354655", "content_hash": "b34b65e62fcb", "message_id": 2151, "sent_at": "2026-06-24T14:16:14+00:00"}, "413582061": {"chat_id": "-1003764354655", "content_hash": "33016b8faa11", "message_id": 2152, "sent_at": "2026-06-24T15:46:15+00:00"}, "413583061": {"chat_id": "-1003764354655", "content_hash": "8a3440f99439", "message_id": 2153, "sent_at": "2026-06-24T16:01:41+00:00"}, "413585061": {"chat_id": "-1003764354655", "content_hash": "bbb5b7ccfd29", "message_id": 2154, "sent_at": "2026-06-24T16:01:41+00:00"}, "413586061": {"chat_id": "-1003764354655", "content_hash": "32a2b8f677c7", "message_id": 2155, "sent_at": "2026-06-24T16:01:41+00:00"}, "413587061": {"chat_id": "-1003764354655", "content_hash": "1bd1c534f7cb", "message_id": 2156, "sent_at": "2026-06-24T16:01:41+00:00"}, "413588061": {"chat_id": "-1003764354655", "content_hash": "d38d2766fd5a", "message_id": 2158, "sent_at": "2026-06-24T16:16:11+00:00"}, "413589061": {"chat_id": "-1003764354655", "content_hash": "d4f85b4c2fc8", "message_id": 2159, "sent_at": "2026-06-24T16:46:09+00:00"}, "413591061": {"chat_id": "-1003764354655", "content_hash": "e59a59bbcdfd", "message_id": 2160, "sent_at": "2026-06-24T16:46:09+00:00"}, "413592061": {"chat_id": "-1003764354655", "content_hash": "af55f3dff15c", "message_id": 2161, "sent_at": "2026-06-24T17:01:30+00:00"}, "413593061": {"chat_id": "-1003764354655", "content_hash": "ed949f80ed6e", "message_id": 2162, "sent_at": "2026-06-24T17:16:11+00:00"}, "413594061": {"chat_id": "-1003764354655", "content_hash": "8540cf23585e", "message_id": 2163, "sent_at": "2026-06-24T17:46:05+00:00"}, "413601061": {"chat_id": "-1003764354655", "content_hash": "6f4028a80342", "message_id": 2164, "sent_at": "2026-06-24T17:46:05+00:00"}, "413602061": {"chat_id": "-1003764354655", "content_hash": "15c54adea1ca", "message_id": 2165, "sent_at": "2026-06-24T17:59:59+00:00"}, "413608061": {"chat_id": "-1003764354655", "content_hash": "b775900ced82", "message_id": 2166, "sent_at": "2026-06-24T18:46:09+00:00"}, "413611061": {"chat_id": "-1003764354655", "content_hash": "0396163868a4", "message_id": 2167, "sent_at": "2026-06-24T19:46:11+00:00"}, "413612061": {"chat_id": "-1003764354655", "content_hash": "1c9f85807d90", "message_id": 2168, "sent_at": "2026-06-24T19:46:11+00:00"}, "413613061": {"chat_id": "-1003764354655", "content_hash": "53f7706175bc", "message_id": 2170, "sent_at": "2026-06-24T20:01:40+00:00"}, "413616061": {"chat_id": "-1003764354655", "content_hash": "6d97ef3f76d9", "message_id": 2171, "sent_at": "2026-06-25T04:16:03+00:00"}, "413617061": {"chat_id": "-1003764354655", "content_hash": "ac0a730ad1f3", "message_id": 2172, "sent_at": "2026-06-25T04:46:13+00:00"}, "413618061": {"chat_id": "-1003764354655", "content_hash": "d812d69c076d", "message_id": 2173, "sent_at": "2026-06-25T05:16:09+00:00"}, "413619061": {"chat_id": "-1003764354655", "content_hash": "4c3548862455", "message_id": 2174, "sent_at": "2026-06-25T05:16:09+00:00"}, "413620061": {"chat_id": "-1003764354655", "content_hash": "44bfd77fcbe2", "message_id": 2175, "sent_at": "2026-06-25T05:46:12+00:00"}, "413624061": {"chat_id": "-1003764354655", "content_hash": "387e14817e72", "message_id": 2176, "sent_at": "2026-06-25T05:46:12+00:00"}, "413625061": {"chat_id": "-1003764354655", "content_hash": "a6d96ff3cdc6", "message_id": 2177, "sent_at": "2026-06-25T06:01:32+00:00"}, "413626061": {"chat_id": "-1003764354655", "content_hash": "ac0a730ad1f3", "message_id": 2178, "sent_at": "2026-06-25T06:46:06+00:00"}, "413628061": {"chat_id": "-1003764354655", "content_hash": "cf82faac560d", "message_id": 2179, "sent_at": "2026-06-25T06:46:06+00:00"}, "413629061": {"chat_id": "-1003764354655", "content_hash": "8bad02652248", "message_id": 2180, "sent_at": "2026-06-25T07:16:07+00:00"}, "413630061": {"chat_id": "-1003764354655", "content_hash": "9d78b65af60f", "message_id": 2181, "sent_at": "2026-06-25T07:16:07+00:00"}, "413631061": {"chat_id": "-1003764354655", "content_hash": "bae4e9a8a63a", "message_id": 2182, "sent_at": "2026-06-25T08:16:12+00:00"}, "413638061": {"chat_id": "-1003764354655", "content_hash": "7732c00255e1", "message_id": 2183, "sent_at": "2026-06-25T09:46:12+00:00"}, "413639061": {"chat_id": "-1003764354655", "content_hash": "a5d6feb78e93", "message_id": 2184, "sent_at": "2026-06-25T10:01:38+00:00"}, "413640061": {"chat_id": "-1003764354655", "content_hash": "cfd6ebf30de7", "message_id": 2185, "sent_at": "2026-06-25T10:01:38+00:00"}, "413641061": {"chat_id": "-1003764354655", "content_hash": "e05d07db9243", "message_id": 2186, "sent_at": "2026-06-25T11:01:32+00:00"}, "413642061": {"chat_id": "-1003764354655", "content_hash": "3728d096784c", "message_id": 2187, "sent_at": "2026-06-25T11:01:32+00:00"}, "413643061": {"chat_id": "-1003764354655", "content_hash": "ab8626ed1049", "message_id": 2188, "sent_at": "2026-06-25T12:16:12+00:00"}, "413645061": {"chat_id": "-1003764354655", "content_hash": "c80d513cc22a", "message_id": 2189, "sent_at": "2026-06-25T13:01:42+00:00"}, "413646061": {"chat_id": "-1003764354655", "content_hash": "6237320146c8", "message_id": 2190, "sent_at": "2026-06-25T13:16:17+00:00"}, "413647061": {"chat_id": "-1003764354655", "content_hash": "ac0a730ad1f3", "message_id": 2191, "sent_at": "2026-06-25T13:46:20+00:00"}, "413648061": {"chat_id": "-1003764354655", "content_hash": "cc58f7d7d624", "message_id": 2192, "sent_at": "2026-06-25T13:46:20+00:00"}, "413649061": {"chat_id": "-1003764354655", "content_hash": "48a85e5c2f71", "message_id": 2193, "sent_at": "2026-06-25T13:46:20+00:00"}, "413652061": {"chat_id": "-1003764354655", "content_hash": "1573b13127fb", "message_id": 2194, "sent_at": "2026-06-25T14:46:09+00:00"}, "413653061": {"chat_id": "-1003764354655", "content_hash": "39ea466361c1", "message_id": 2195, "sent_at": "2026-06-25T14:46:09+00:00"}, "413657061": {"chat_id": "-1003764354655", "content_hash": "0c3956a9a939", "message_id": 2196, "sent_at": "2026-06-25T15:01:42+00:00"}, "413659061": {"chat_id": "-1003764354655", "content_hash": "e1ff8528bd50", "message_id": 2197, "sent_at": "2026-06-25T15:16:17+00:00"}, "413660061": {"chat_id": "-1003764354655", "content_hash": "6b77f2257c61", "message_id": 2198, "sent_at": "2026-06-25T15:46:16+00:00"}, "413661061": {"chat_id": "-1003764354655", "content_hash": "3c4e8d29f22d", "message_id": 2199, "sent_at": "2026-06-25T15:46:16+00:00"}, "413662061": {"chat_id": "-1003764354655", "content_hash": "e3603c51f618", "message_id": 2200, "sent_at": "2026-06-25T17:01:30+00:00"}, "413663061": {"chat_id": "-1003764354655", "content_hash": "674486012a8d", "message_id": 2201, "sent_at": "2026-06-25T17:46:09+00:00"}, "413665061": {"chat_id": "-1003764354655", "content_hash": "ef6a5f3a91a6", "message_id": 2202, "sent_at": "2026-06-25T17:46:09+00:00"}, "413666061": {"chat_id": "-1003764354655", "content_hash": "1bede28a3736", "message_id": 2203, "sent_at": "2026-06-25T18:01:53+00:00"}, "413668061": {"chat_id": "-1003764354655", "content_hash": "b358c1bc2bdf", "message_id": 2204, "sent_at": "2026-06-25T18:01:53+00:00"}, "413669061": {"chat_id": "-1003764354655", "content_hash": "4f21d4e1b6ac", "message_id": 2205, "sent_at": "2026-06-25T18:16:13+00:00"}, "413671061": {"chat_id": "-1003764354655", "content_hash": "c1713b115b78", "message_id": 2206, "sent_at": "2026-06-25T18:46:16+00:00"}, "413672061": {"chat_id": "-1003764354655", "content_hash": "82ac8497ec80", "message_id": 2207, "sent_at": "2026-06-25T19:16:22+00:00"}, "413674061": {"chat_id": "-1003764354655", "content_hash": "4596621cfac0", "message_id": 2208, "sent_at": "2026-06-25T20:16:11+00:00"}, "413675061": {"chat_id": "-1003764354655", "content_hash": "051ad0396ddb", "message_id": 2209, "sent_at": "2026-06-26T03:01:27+00:00"}, "413678061": {"chat_id": "-1003764354655", "content_hash": "41652a04bd43", "message_id": 2210, "sent_at": "2026-06-26T06:16:02+00:00"}, "413681061": {"chat_id": "-1003764354655", "content_hash": "8f03811662f4", "message_id": 2211, "sent_at": "2026-06-26T06:46:10+00:00"}}